cfntagger/__init__.py
cfntagger/cfntagger.py
cfntagger/pytest.py
cfntagger/ruamel.py
cfntagger/test-json.py
cfntagger/version.py
cfntagger-0.10.3.data/scripts/cfntagger
tests/__init__.py
tests/test_canary.py
tests/test_comments.py
tests/test_config.py
tests/test_ec2.py
tests/test_empty_cfntags.py
tests/test_get_kv.py
tests/test_git.py
tests/test_jsontags.py
tests/test_noproperties.py
tests/test_s3.py
tests/test_s3_output_is_cfn.py
tests/test_supports_tags.py
tests/unittest.py
cfntagger-0.10.3.dist-info/LICENSE
cfntagger-0.10.3.dist-info/METADATA
cfntagger-0.10.3.dist-info/WHEEL
cfntagger-0.10.3.dist-info/top_level.txt
cfntagger-0.10.3.dist-info/RECORD
