Metadata-Version: 2.1
Name: cfntagger
Version: 0.10.3
Summary: A Cloudformation tagging tool
Home-page: https://github.com/kristofwillen/cfntagger
Author: Kristof Willen
Author-email: kristof.willen@gmail.com
License: GPL
Keywords: cloudformation tagging
Classifier: Programming Language :: Python :: 3
Classifier: Development Status :: 5 - Production/Stable
Classifier: Intended Audience :: Developers
Classifier: License :: OSI Approved :: GNU General Public License v3 (GPLv3)
License-File: LICENSE
Requires-Dist: ruamel.yaml >=0.17.24
Requires-Dist: colorama >=0.4.4
Requires-Dist: gitpython >=3.1.34
